{"position":{"x":96,"y":64},"trees":["regular_1","regular_1","regular_1","regular_1"],"objects":[{"pos":{"x":7,"y":1},"sprite":"big_016"},{"pos":{"x":17,"y":14},"sprite":"hollow_044"},{"pos":{"x":20,"y":10},"sprite":"big_42"},{"pos":{"x":8,"y":29},"sprite":"big_017"},{"pos":{"x":27,"y":30},"sprite":"big_010"},{"pos":{"x":28,"y":0},"sprite":"hollow_044"},{"pos":{"x":30,"y":27},"sprite":"big_05"},{"pos":{"x":29,"y":16},"sprite":"big_41"},{"pos":{"x":2,"y":18},"sprite":"hollow_040"},{"pos":{"x":11,"y":2},"sprite":"hollow_060"},{"pos":{"x":12,"y":3},"sprite":"big_39"},{"pos":{"x":1,"y":12},"sprite":"big_05"},{"pos":{"x":9,"y":20},"sprite":"hollow_058"},{"pos":{"x":10,"y":7},"sprite":"hollow_050"},{"pos":{"x":26,"y":13},"sprite":"big_05"},{"pos":{"x":21,"y":24},"sprite":"hollow_080"},{"pos":{"x":22,"y":26},"sprite":"big_41"},{"pos":{"x":25,"y":25},"sprite":"hollow_061"}]}