{"position":{"x":480,"y":192},"trees":["regular_6"],"objects":[{"pos":{"x":0,"y":16},"sprite":"hollow_04"},{"pos":{"x":11,"y":29},"sprite":"hollow_021"},{"pos":{"x":15,"y":30},"sprite":"hollow_026"},{"pos":{"x":8,"y":11},"sprite":"hollow_04"},{"pos":{"x":7,"y":26},"sprite":"hollow_019"},{"pos":{"x":9,"y":10},"sprite":"hollow_017"},{"pos":{"x":10,"y":7},"sprite":"hollow_058"},{"pos":{"x":1,"y":14},"sprite":"hollow_017"},{"pos":{"x":12,"y":22},"sprite":"hollow_028"},{"pos":{"x":2,"y":0},"sprite":"hollow_04"},{"pos":{"x":3,"y":17},"sprite":"hollow_0802"}]}